<property xmlns="http://faculty.washington.edu/tgis/xml/xsd/modules/xsd4md/"
    xmlns:xsi="http://www.w3.org/2001/XMLSchema-instance"
    xmlns:xs="http://www.w3.org/2001/XMLSchema"
    xsi:schemaLocation="http://faculty.washington.edu/tgis/xml/xsd/modules/xsd4md/ http://faculty.washington.edu/tgis/xml/xsd/modules/xsd4md/schema-4-properties-0.1.xsd">
    <labels>
        <platformIndependent>staffNotes</platformIndependent>
        <dc>none</dc>
    </labels>
    <cdm>
        <label>Staff Notes</label>
        <cdmDatatype>text</cdmDatatype>
        <cdmLarge>no</cdmLarge>
        <searchable>no</searchable>
        <hidden>yes</hidden>
        <required>no</required>
        <cdmControlledVocab>no</cdmControlledVocab>
    </cdm>
    <dspace>
        <dspaceProperty/>
    </dspace>
    <descriptions>
        <definition co="no">
            <para>Notes for staff only, notes of an administrative nature.</para>
        </definition>
        <instructions co="no">
            <para>Input your staff notes however you wish.</para>
        </instructions>
        
    </descriptions>
    <examples>
        <example co="no">
            <para>Joe, could you look at this one?</para>
            <para>Still need to research the difference between the saws pictured.</para>
        </example>
        
        <!-- customization here is flawed.
             I think we need
             <customizations>
                 <description | example>
                     <para @co @dd @paraDec @paraEx> REPEATABLE
                         <para>
        -->
        
    </examples>
    <additionalInfo>
        <admin>
            <para/>
        </admin>
        <generalNotes>
            <para/>
        </generalNotes>
    </additionalInfo>
    <marc>
        <dcgMarcMapping/>
        <marcNotes>
            <para/>
        </marcNotes>
    </marc>
    <xsd>
        <typeAttribute>xs:string</typeAttribute>
        <complexType/>
        
    </xsd>
    <rdf>
        <sameAs/>
    </rdf>
    <history>
        <dateCreated>
            
            <range>
                <start>2000-01-01</start>
                <end>2017-01-12</end>
            </range>
        </dateCreated>
        <created4Coll>Special Collections Photograph Collections</created4Coll>
        <justification>Staff needed a way to communicate about administering the resource inside CONTENTdm, so we created this property.</justification>
        <changeLog>
            <change/>
        </changeLog>
    </history>
</property>